dog_server/__init__.py
dog_server/__main__.py
dog_server/_main.py
dog_server/dog
dog_server-0.1a0.dist-info/METADATA
dog_server-0.1a0.dist-info/WHEEL
dog_server-0.1a0.dist-info/entry_points.txt
dog_server-0.1a0.dist-info/top_level.txt
dog_server-0.1a0.dist-info/RECORD
