Metadata-Version: 2.1
Name: dog-server
Version: 0.1a0
Summary: Dog - HTTP proxy and process manager with zero-downtime upgrades
Author: Simon Willison
License: MIT
Requires-Python: >=3.8
Classifier: Development Status :: 4 - Beta
Classifier: Environment :: Console
Classifier: License :: OSI Approved :: MIT License
Classifier: Operating System :: MacOS
Classifier: Operating System :: Microsoft :: Windows
Classifier: Operating System :: POSIX :: Linux
Classifier: Programming Language :: Python :: 3
